{
    "d": {
        "__type": "Memocast.Web.services.payments.PaymentResponse",
        "Reply": {
            "merchantReferenceCode": "a7b5ff7949dd464986be5466ef3b16aa",
            "requestID": "4919242466496802504008",
            "decision": "ACCEPT",
            "reasonCode": "100",
            "missingField": null,
            "invalidField": null,
            "requestToken": "Ahj//wSTCqw0AAPmVL1IFCrZq0bOXLFkxsRZdewxa2mMuNGT+yXOlJoBT+yXOlJrSBfy272GTSSbbvPFGFwwJyYVWGgAB8ypepAA1hQK",
            "purchaseTotals": {
                "currency": "USD",
                "discountAmount": null,
                "taxAmount": null,
                "dutyAmount": null,
                "grandTotalAmount": null,
                "freightAmount": null,
                "foreignAmount": null,
                "foreignCurrency": null,
                "exchangeRate": null,
                "exchangeRateTimeStamp": null,
                "additionalAmountType0": null,
                "additionalAmount0": null,
                "additionalAmountType1": null,
                "additionalAmount1": null,
                "additionalAmountType2": null,
                "additionalAmount2": null,
                "additionalAmountType3": null,
                "additionalAmount3": null,
                "additionalAmountType4": null,
                "additionalAmount4": null
            },
            "deniedPartiesMatch": null,
            "ccAuthReply": {
                "reasonCode": "100",
                "amount": "19.95",
                "authorizationCode": "0XXXXA",
                "avsCode": "2",
                "avsCodeRaw": "0",
                "cvCode": null,
                "cvCodeRaw": null,
                "personalIDCode": null,
                "authorizedDateTime": "2017-04-11T15:24:06Z",
                "processorResponse": "00",
                "bmlAccountNumber": null,
                "authFactorCode": null,
                "reconciliationID": null,
                "fundingTotals": null,
                "fxQuoteID": null,
                "fxQuoteRate": null,
                "fxQuoteType": null,
                "fxQuoteExpirationDateTime": null,
                "authRecord": null,
                "merchantAdviceCode": null,
                "merchantAdviceCodeRaw": null,
                "cavvResponseCode": null,
                "cavvResponseCodeRaw": null,
                "authenticationXID": null,
                "authorizationXID": null,
                "processorCardType": null,
                "accountBalance": null,
                "forwardCode": null,
                "enhancedDataEnabled": null,
                "referralResponseNumber": null,
                "subResponseCode": null,
                "approvedAmount": null,
                "creditLine": null,
                "approvedTerms": null,
                "paymentNetworkTransactionID": null,
                "cardCategory": null,
                "ownerMerchantID": null,
                "requestAmount": null,
                "requestCurrency": null,
                "accountBalanceCurrency": null,
                "accountBalanceSign": null,
                "affluenceIndicator": null,
                "evEmail": null,
                "evPhoneNumber": null,
                "evPostalCode": null,
                "evName": null,
                "evStreet": null,
                "evEmailRaw": null,
                "evPhoneNumberRaw": null,
                "evPostalCodeRaw": null,
                "evNameRaw": null,
                "evStreetRaw": null,
                "cardGroup": null,
                "posData": null,
                "transactionID": null
            },
            "ccCaptureReply": {
                "reasonCode": "100",
                "requestDateTime": "2017-04-11T15:24:06Z",
                "amount": "19.95",
                "reconciliationID": "654699121XEKWX15Z1KFF",
                "fundingTotals": null,
                "fxQuoteID": null,
                "fxQuoteRate": null,
                "fxQuoteType": null,
                "fxQuoteExpirationDateTime": null,
                "purchasingLevel3Enabled": null,
                "enhancedDataEnabled": null
            },
            "ccCreditReply": null,
            "ccAuthReversalReply": null,
            "ccAutoAuthReversalReply": null,
            "ccDCCReply": null,
            "ecDebitReply": null,
            "ecCreditReply": null,
            "ecAuthenticateReply": null,
            "payerAuthEnrollReply": null,
            "payerAuthValidateReply": null,
            "taxReply": null,
            "afsReply": null,
            "davReply": null,
            "exportReply": null,
            "fxRatesReply": null,
            "bankTransferReply": null,
            "bankTransferRefundReply": null,
            "bankTransferRealTimeReply": null,
            "directDebitMandateReply": null,
            "directDebitReply": null,
            "directDebitValidateReply": null,
            "directDebitRefundReply": null,
            "paySubscriptionCreateReply": null,
            "paySubscriptionUpdateReply": null,
            "paySubscriptionEventUpdateReply": null,
            "paySubscriptionRetrieveReply": null,
            "paySubscriptionDeleteReply": null,
            "payPalPaymentReply": null,
            "payPalCreditReply": null,
            "voidReply": null,
            "pinlessDebitReply": null,
            "pinlessDebitValidateReply": null,
            "pinlessDebitReversalReply": null,
            "payPalButtonCreateReply": null,
            "payPalPreapprovedPaymentReply": null,
            "payPalPreapprovedUpdateReply": null,
            "riskUpdateReply": null,
            "fraudUpdateReply": null,
            "decisionReply": null,
            "reserved": null,
            "payPalRefundReply": null,
            "payPalAuthReversalReply": null,
            "payPalDoCaptureReply": null,
            "payPalEcDoPaymentReply": null,
            "payPalEcGetDetailsReply": null,
            "payPalEcSetReply": null,
            "payPalAuthorizationReply": null,
            "payPalEcOrderSetupReply": null,
            "payPalUpdateAgreementReply": null,
            "payPalCreateAgreementReply": null,
            "payPalDoRefTransactionReply": null,
            "chinaPaymentReply": null,
            "chinaRefundReply": null,
            "boletoPaymentReply": null,
            "apInitiateReply": null,
            "apCheckStatusReply": null,
            "receiptNumber": null,
            "additionalData": null,
            "solutionProviderTransactionID": null
        },
        "Error": null
    }
}
